Metadata-Version: 2.1
Name: dbt-postgres-python
Version: 1.7.17
Summary: Run python scripts from any dbt project. This project is based on the project https://github.com/fal-ai/fal initially authored by FAL.AI.
Home-page: https://github.com/kudryk/dbt-postgres-python
Keywords: dbt,pandas,fal,runtime
Author: Features & Labels
Author-email: hello@fal.ai
Requires-Python: >=3.8,<4.0
Classifier: Development Status :: 4 - Beta
Classifier: Programming Language :: Python :: 3
Classifier: Programming Language :: Python :: 3.8
Classifier: Programming Language :: Python :: 3.9
Classifier: Programming Language :: Python :: 3.10
Classifier: Programming Language :: Python :: 3.11
Provides-Extra: postgres
Provides-Extra: teleport
Requires-Dist: dbt-core (>=1.7,<=1.7.16)
Requires-Dist: fal (>=0.10.0,<0.11.0)
Requires-Dist: importlib-metadata (>=6.11.0,<7.0.0)
Requires-Dist: numpy (<2)
Requires-Dist: packaging (>=23)
Requires-Dist: pandas (>=1.5.3,<2.0.0)
Requires-Dist: s3fs (>=2022.8.2) ; extra == "teleport"
Requires-Dist: sqlalchemy (>=1.4.52,<2.0.0)
Requires-Dist: virtualenv (>=20.21.1,<21.0.0)
Project-URL: Repository, https://github.com/kudryk/dbt-postgres-python
